setup.py
tjsonb/_init_.py
tjsonb.egg-info/PKG-INFO
tjsonb.egg-info/SOURCES.txt
tjsonb.egg-info/dependency_links.txt
tjsonb.egg-info/top_level.txt