Metadata-Version: 2.4
Name: tjsonb
Version: 0.0.1
Summary: Python bindings for tjsonb PostgreSQL extension
Requires-Python: >=3.7
Dynamic: requires-python
Dynamic: summary
